llm_client_redis/__init__.py
llm_client_redis/chat_session_main.py
llm_client_redis/llm_client.py
llm_client_redis/llm_client_dir_sender_main.py
llm_client_redis/llm_client_dirs_watcher_main.py
llm_client_redis/llm_restful_client_main.py
llm_client_redis/cmd_chat/__init__.py
llm_client_redis/cmd_chat/chat_session.py
llm_client_redis/cmd_chat/command_def.py
llm_client_redis/cmd_chat/cmd_templates/__init__.py
llm_client_redis/cmd_chat/cmd_templates/send_template_cmd.py
llm_client_redis/cmd_chat/cmd_templates/show_text_block_cmd.py
llm_client_redis/cmd_chat/cmd_templates/text_block_command.py
llm_client_redis/tools/__init__.py
llm_client_redis/tools/init_config_tools.py
llm_client_redis/tools/llm_redis_manager.py
llm_client_redis/tools/llm_resources_tools.py
llm_client_redis/tools/output_tools.py
llm_client_redis/tools/time_controller.py
llm_client_redis-0.1.9.dist-info/licenses/LICENSE
llm_client_redis-0.1.9.dist-info/METADATA
llm_client_redis-0.1.9.dist-info/WHEEL
llm_client_redis-0.1.9.dist-info/entry_points.txt
llm_client_redis-0.1.9.dist-info/top_level.txt
llm_client_redis-0.1.9.dist-info/RECORD
