Metadata-Version: 2.4
Name: llm_client_redis
Version: 0.1.9
Summary: LLM redis中介的客户端程序
Author-email: Fang JiaWei <fjw12998@hotmail.com>
License-Expression: GPL-3.0-or-later
Project-URL: Homepage, https://gitee.com/sky_flash/llm_client_redis
Project-URL: Documentation, https://gitee.com/sky_flash/llm_client_redis/docs
Classifier: Programming Language :: Python :: 3
Classifier: Programming Language :: Python :: 3.9
Classifier: Programming Language :: Python :: 3.10
Classifier: Programming Language :: Python :: 3.11
Classifier: Programming Language :: Python :: 3.12
Classifier: Operating System :: OS Independent
Requires-Python: >=3.9
License-File: LICENSE
Requires-Dist: langchain_core<0.4.0,>=0.3.72
Requires-Dist: pytest<9.0.0,==8.4.1
Requires-Dist: redis<6.0.0,==5.3.0
Requires-Dist: Requests<3.0.0,==2.32.4
Requires-Dist: fastapi<0.117.0,>=0.116.1
Requires-Dist: uvicorn<0.36.0,>=0.35.0
Requires-Dist: gunicorn<24.0.0,>=23.0.0
Requires-Dist: pydantic<3.0.0,>=2.11.7
Requires-Dist: watchfiles<2.0.0,>=1.1.0
Requires-Dist: llm_tokenizers>=0.1.2
Dynamic: license-file
